piexif/__init__.py
piexif/_common.py
piexif/_dump.py
piexif/_exceptions.py
piexif/_exif.py
piexif/_insert.py
piexif/_load.py
piexif/_remove.py
piexif/_transplant.py
piexif/_webp.py
piexif/helper.py
piexif-1.1.2.dist-info/DESCRIPTION.rst
piexif-1.1.2.dist-info/METADATA
piexif-1.1.2.dist-info/RECORD
piexif-1.1.2.dist-info/WHEEL
piexif-1.1.2.dist-info/metadata.json
piexif-1.1.2.dist-info/top_level.txt
