Metadata-Version: 1.1
Name: piexif
Version: 1.1.2
Summary: To simplify exif manipulations with python. Writing, reading, and more...
Home-page: https://github.com/hMatoba/Piexif
Author: hMatoba
Author-email: hiroaki.mtb@outlook.com
License: MIT
Keywords: exif,jpeg
Platform: UNKNOWN
Classifier: Development Status :: 5 - Production/Stable
Classifier: Operating System :: OS Independent
Classifier: Programming Language :: Python :: 2.7
Classifier: Programming Language :: Python :: 3.3
Classifier: Programming Language :: Python :: 3.4
Classifier: Programming Language :: Python :: 3.5
Classifier: Programming Language :: Python :: 3.6
Classifier: Programming Language :: Python :: Implementation :: CPython
Classifier: Programming Language :: Python :: Implementation :: IronPython
Classifier: Programming Language :: Python :: Implementation :: PyPy
Classifier: License :: OSI Approved :: MIT License
Classifier: Topic :: Multimedia
Classifier: Topic :: Printing
